<Alloy>
	<View id="scheduleDetailWindow" title="Schedule item" class="container">
		<View class="metadata">				
			<View class="labelLine">
				<Label class="metaBoldLabel">Date / Time:</Label>
				<Label id="dateLabel" class="metalabel">Date / Time</Label>
			</View>
			
			<View class="labelLine">
				<Label class="metaBoldLabel">Room:</Label>
				<Label id="roomLabel" class="metalabel">Room</Label>
			</View>				
		</View>
        <ScrollView class="detailScroll">
			<View class="contentContainer">
				<Label id="titleLabel" class="header">Title</Label>
				<Label id="descriptionLabel" class="content"></Label>
				
				<View id="speakerContainer">
					
				</View>
			</View>
			<ImageView image="/images/footer-upper.png"></ImageView>
		</ScrollView>
	</View>
</Alloy>